dist_info/__init__.py
dist_info-0.1.1.data/scripts/dist-info
dist_info-0.1.1.dist-info/LICENSE
dist_info-0.1.1.dist-info/METADATA
dist_info-0.1.1.dist-info/WHEEL
dist_info-0.1.1.dist-info/top_level.txt
dist_info-0.1.1.dist-info/RECORD
