Metadata-Version: 2.1
Name: dist-info
Version: 0.1.1
Summary: dist-info - получить информацию об установленном дистрибутиве
Home-page: https://github.com/darviarush/python-dist-info
Author: Kosmina O. Yaroslav
Author-email: darviarush@mail.ru
License: MIT
Platform: any
Classifier: Development Status :: 5 - Production/Stable
Classifier: Topic :: Text Processing
Classifier: License :: OSI Approved :: MIT License
Classifier: Operating System :: OS Independent
Classifier: Programming Language :: Python :: 3
Classifier: Programming Language :: Python :: 3.3
Classifier: Programming Language :: Python :: 3.4
Classifier: Programming Language :: Python :: 3.5
Classifier: Programming Language :: Python :: 3.6
Classifier: Programming Language :: Python :: 3.7
Requires-Python: >=3.6
